s3sfe/__init__.py
s3sfe/filesyncer.py
s3sfe/restorer.py
s3sfe/runner.py
s3sfe/runstats.py
s3sfe/s3.py
s3sfe/utils.py
s3sfe/version.py
s3sfe/tests/__init__.py
s3sfe/tests/test_filesyncer.py
s3sfe/tests/test_restorer.py
s3sfe/tests/test_runner.py
s3sfe/tests/test_runstats.py
s3sfe/tests/test_s3.py
s3sfe/tests/test_utils.py
s3sfe/tests/test_version.py
s3sfe-0.1.1.dist-info/DESCRIPTION.rst
s3sfe-0.1.1.dist-info/METADATA
s3sfe-0.1.1.dist-info/RECORD
s3sfe-0.1.1.dist-info/WHEEL
s3sfe-0.1.1.dist-info/entry_points.txt
s3sfe-0.1.1.dist-info/metadata.json
s3sfe-0.1.1.dist-info/top_level.txt
