Metadata-Version: 2.0
Name: s3sfe
Version: 0.1.1
Summary: s3sfe (S3 Sync Filelist Encrypted) Sync a list of files to S3, using server-side encryption with customer-provided keys.
Home-page: https://github.com/jantman/s3sfe
Author: Jason Antman
Author-email: jason@jasonantman.com
License: UNKNOWN
Keywords: aws s3 backup encrypted sync
Platform: UNKNOWN
Classifier: Development Status :: 3 - Alpha
Classifier: Environment :: Console
Classifier: Intended Audience :: Developers
Classifier: Intended Audience :: End Users/Desktop
Classifier: Intended Audience :: Information Technology
Classifier: Intended Audience :: System Administrators
Classifier: License :: OSI Approved :: GNU Affero General Public License v3 or later (AGPLv3+)
Classifier: Natural Language :: English
Classifier: Operating System :: POSIX
Classifier: Programming Language :: Python
Classifier: Programming Language :: Python :: 2.7
Classifier: Programming Language :: Python :: 3
Classifier: Programming Language :: Python :: 3.3
Classifier: Programming Language :: Python :: 3.4
Classifier: Programming Language :: Python :: 3.5
Classifier: Programming Language :: Python :: 3.6
Classifier: Topic :: System :: Archiving :: Backup
Classifier: Topic :: Utilities
Requires-Dist: boto3
Requires-Dist: humanize
